LICENSE
MANIFEST.in
setup.py
geocode/__init__.py
geocode/api.py
twentytab_geocode.egg-info/PKG-INFO
twentytab_geocode.egg-info/SOURCES.txt
twentytab_geocode.egg-info/dependency_links.txt
twentytab_geocode.egg-info/requires.txt
twentytab_geocode.egg-info/top_level.txt