Metadata-Version: 1.0
Name: twentytab-geocode
Version: 0.1
Summary: It's a simple python client that uses google geocode api
Home-page: https://github.com/20tab/twentytab-geocode
Author: 20tab S.r.l.
Author-email: info@20tab.com
License: MIT License
Platform: UNKNOWN
